templateco_plugin_plugin/README.md
templateco_plugin_plugin/__init__.py
templateco_plugin_plugin/poetry/pyproject.toml.jinja2
templateco_plugin_plugin/poetry.lock
templateco_plugin_plugin/pyproject.toml
templateco_plugin_plugin/template/README.md.jinja2
templateco_plugin_plugin/template/{% if use_subfolder %}{{ prefix }}_{{ name }}_plugin/{% endif %}__init__.py.jinja2
templateco_plugin_plugin/template/{% if use_subfolder %}{{ prefix }}_{{ name }}_plugin/{% endif %}template/.gitkeep.jinja2
templateco_plugin_plugin/tooling/.editorconfig.jinja2
templateco_plugin_plugin/tooling/.gitignore.jinja2
templateco_plugin_plugin/tooling/.tool-versions.jinja2
templateco_plugin_plugin/tooling/Makefile.jinja2
templateco_plugin_plugin/tooling/setup.cfg.jinja2
templateco_plugin_plugin-0.1.2.dist-info/WHEEL
templateco_plugin_plugin-0.1.2.dist-info/METADATA
templateco_plugin_plugin-0.1.2.dist-info/RECORD
